{
    "users": [
        {
            "id": 0,
            "name": "John Doe",
            "description": "unknown"
        },
        {
            "id": 1,
            "name": "Jane Doe",
            "description": "unknown wife"
        },
        {
            "id": 2,
            "name": "Jan Kowalski",
            "description": "basic human"
        },
        {
            "id": 3,
            "name": "Jan Nowak",
            "description": "basic human as well"
        },
        {
            "id": 4,
            "name": "Simon Minter",
            "description": "some youtuber or sth"
        },
        {
            "id": 5,
            "name": "Keanu Reeves",
            "description": "basically best human alive"
        },
        {
            "id": 6,
            "name": "Bruh",
            "description": "bruh"
        },
        {
            "id": 7,
            "name": "Last",
            "description": "yea he last"
        }
    ],
    "images": [
        {
            "id": 0,
            "name": "tree-736885__480.jpg"
        },
        {
            "id": 1,
            "name": "983794168.jpg"
        },
        {
            "id": 2,
            "name": "04-nature_721703848.jpg"
        },
        {
            "id": 3,
            "name": "photo-1503023345310-bd7c1de61c7d.jpg"
        },
        {
            "id": 4,
            "name": "field-6574455__480.jpg"
        },
        {
            "id": 5,
            "name": "pexels-photo-674010.jpeg"
        },
        {
            "id": 6,
            "name": "photo-1541963463532-d68292c34b19.jpg"
        }
    ]
}